SlyMastodon/__init__.py
SlyMastodon/__main__.py
SlyMastodon/mastodon.py
SlyMastodon/serialization.py
SlyMastodon-0.0.1.dist-info/LICENSE
SlyMastodon-0.0.1.dist-info/METADATA
SlyMastodon-0.0.1.dist-info/WHEEL
SlyMastodon-0.0.1.dist-info/top_level.txt
SlyMastodon-0.0.1.dist-info/RECORD
