Metadata-Version: 2.1
Name: SlyMastodon
Version: 0.0.1
Summary: No-boilerplate, async and typed Mastodon access 😋
Author: Dunkyl 🔣🔣
License: MIT License
Project-URL: Homepage, https://github.com/dunkyl/SlyMastodon-Python
Project-URL: Repository, https://github.com/dunkyl/SlyMastodon-Python
Project-URL: Bug Tracker, https://github.com/dunkyl/SlyMastodon-Python/issues
Requires-Python: >=3.11
License-File: LICENSE
Requires-Dist: SlyAPI (>=0.4.5)
Provides-Extra: dev
Requires-Dist: pytest ; extra == 'dev'
Requires-Dist: pytest-asyncio ; extra == 'dev'
Requires-Dist: sphinx ; extra == 'dev'
Requires-Dist: myst-parser ; extra == 'dev'
Requires-Dist: furo ; extra == 'dev'
Requires-Dist: sphinxcontrib-trio ; extra == 'dev'
Requires-Dist: sphinx-copybutton ; extra == 'dev'
Requires-Dist: sphinxext-opengraph ; extra == 'dev'
